<?xml version='1.0' encoding='utf-8' ?>
<odoo>

    <record model="base.automation" id="action_send_email">
        <field name="active" eval="True" />
        <field name="name">New Lead Warning</field>
        <field name="model_id" ref="crm.model_crm_lead" />
        <field name="trigger">on_create</field>
        <field name="state">email</field>
        <field name="filter_domain">[["type","=","lead"]]</field>
        <field name="template_id" ref="crm_lead_new_email.email_template" />
    </record>

</odoo>
